README
setup.py
django_seatbelt/__init__.py
django_seatbelt/allow_callbacks.py
django_seatbelt/seatbelt.py
django_seatbelt/tests.py
django_seatbelt.egg-info/PKG-INFO
django_seatbelt.egg-info/SOURCES.txt
django_seatbelt.egg-info/dependency_links.txt
django_seatbelt.egg-info/top_level.txt
django_seatbelt.egg-info/zip-safe